LICENSE
pyuiauto/__init__.py
pyuiauto/application.py
pyuiauto/base/application.py
pyuiauto/base/components.py
pyuiauto/components.py
pyuiauto/exceptions.py
pyuiauto/mac/__init__.py
pyuiauto/mac/application.py
pyuiauto/mac/components.py
pyuiauto/wait.py
pyuiauto/win/__init__.py
pyuiauto/win/application.py
pyuiauto/win/components.py
pyuiauto-0.1.12.dist-info/LICENSE
pyuiauto-0.1.12.dist-info/METADATA
pyuiauto-0.1.12.dist-info/WHEEL
pyuiauto-0.1.12.dist-info/RECORD
