Metadata-Version: 2.1
Name: pyUIauto
Version: 0.1.12
Summary: Python UI Automation library, for cross-platform applications, interfacing through the accessibility API
Home-page: https://github.com/harveyf2801/pyUIauto
License: GPL-3.0-only
Keywords: automation,accessibility,cross-platform,ui,desktop,pywinauto,atomac
Author: Harvey Fretwell
Author-email: hgfretwell@gmail.com
Maintainer: Harvey Fretwell
Maintainer-email: hgfretwell@gmail.com
Requires-Python: >=3.9,<4.0
Classifier: License :: OSI Approved :: GNU General Public License v3 (GPLv3)
Classifier: Programming Language :: Python :: 3
Classifier: Programming Language :: Python :: 3.9
Classifier: Programming Language :: Python :: 3.10
Classifier: Programming Language :: Python :: 3.11
Classifier: Programming Language :: Python :: 3.12
Requires-Dist: atomacos (>=3.3.0,<4.0.0) ; sys_platform == "darwin"
Requires-Dist: importlib-metadata (>=6.6.0,<7.0.0)
Requires-Dist: pathlib (>=1.0.1,<2.0.0)
Requires-Dist: pyautogui (==0.9.41)
Requires-Dist: pywinauto (>=0.6.8,<0.7.0) ; sys_platform == "win32"
Project-URL: Repository, https://github.com/harveyf2801/pyUIauto
